cosmosim-2.5.3.dist-info/RECORD
cosmosim-2.5.3.dist-info/WHEEL
cosmosim-2.5.3.dist-info/top_level.txt
cosmosim-2.5.3.dist-info/METADATA
cosmosim-2.5.3.dist-info/licenses/LICENSE
cosmosim-2.5.3.data/data/CMakeLists.txt
cosmosim-2.5.3.data/data/requirements.txt
cosmosim-2.5.3.data/data/pyproject.toml
cosmosim-2.5.3.data/data/requirements-build.txt
cosmosim-2.5.3.data/data/setup.py
cosmosim-2.5.3.data/data/python/sieamplitudes.py
cosmosim-2.5.3.data/data/python/amplitudessimplify.py
cosmosim-2.5.3.data/data/python/siediff.py
cosmosim-2.5.3.data/data/python/amplitudes2.py
cosmosim-2.5.3.data/data/python/amplitudes.py
cosmosim-2.5.3.data/data/python/README.md
cosmosim-2.5.3.data/data/python/sieorig.py
cosmosim-2.5.3.data/data/python/.gitignore
cosmosim-2.5.3.data/data/python/amplitudessim.py
cosmosim-2.5.3.data/data/python/libamplitudes.py
cosmosim-2.5.3.data/data/python/compare.py
cosmosim-2.5.3.data/data/include/cosmosim/Roulette.h
cosmosim-2.5.3.data/data/include/cosmosim/Lens.h
cosmosim-2.5.3.data/data/include/cosmosim/PixMapLens.h
cosmosim-2.5.3.data/data/include/cosmosim/Source.h
cosmosim-2.5.3.data/data/include/cosmosim/Simulator.h
cosmosim-2.5.3.data/data/Datasets/mask.csv
cosmosim-2.5.3.data/data/Datasets/triangle2.csv
cosmosim-2.5.3.data/data/Datasets/sis.csv
cosmosim-2.5.3.data/data/Datasets/sie.csv
cosmosim-2.5.3.data/data/Datasets/dataset.toml
cosmosim-2.5.3.data/data/Datasets/README.md
cosmosim-2.5.3.data/data/Datasets/.gitignore
cosmosim-2.5.3.data/data/Datasets/triangle.csv
cosmosim-2.5.3.data/data/Datasets/debug.csv
cosmosim-2.5.3.data/data/Datasets/performance.py
cosmosim-2.5.3.data/data/Datasets/roulletedemo.csv
cosmosim-2.5.3.data/data/Setup/idun.sh
cosmosim-2.5.3.data/data/Setup/idunbuild.sh
cosmosim-2.5.3.data/data/Setup/pypi.sh
cosmosim-2.5.3.data/data/Setup/cibuildwheel.sh
cosmosim-2.5.3.data/data/Setup/testvenv.sh
cosmosim-2.5.3.data/data/Setup/README.md
cosmosim-2.5.3.data/data/Setup/build.sh
cosmosim-2.5.3.data/data/Setup/buildvenv.sh
cosmosim-2.5.3.data/data/Setup/venv.sh
cosmosim-2.5.3.data/data/RegressionTest/makefile-template
cosmosim-2.5.3.data/data/src/CosmoSim.egg-info/PKG-INFO
cosmosim-2.5.3.data/data/src/CosmoSim.egg-info/SOURCES.txt
cosmosim-2.5.3.data/data/src/CosmoSim.egg-info/requires.txt
cosmosim-2.5.3.data/data/src/CosmoSim.egg-info/top_level.txt
cosmosim-2.5.3.data/data/src/CosmoSim.egg-info/dependency_links.txt
