Metadata-Version: 2.4
Name: CosmoSim
Version: 2.5.3
Summary: Simulator of Gravitational Lenses
Author: Hans Georg Schaathun et al
Author-email: Hans Georg Schaathun <georg+github@schaathun.net>
License-Expression: MIT
Project-URL: Homepage, https://github.com/CosmoAI-AES/CosmoSim
Project-URL: Issues, https://github.com/CosmoAI-AES/CosmoSim/issues
Keywords: cosmology,gravitational lensing,simulation
Classifier: Programming Language :: Python :: 3
Classifier: Programming Language :: C++
Classifier: Development Status :: 4 - Beta
Classifier: Intended Audience :: Science/Research
Classifier: Topic :: Scientific/Engineering :: Physics
Classifier: Topic :: Software Development :: Libraries :: Python Modules
Requires-Python: >=3.11
License-File: LICENSE
Requires-Dist: sympy>=1.13
Requires-Dist: numpy
Requires-Dist: matplotlib
Requires-Dist: opencv-python
Requires-Dist: pandas
Dynamic: author
Dynamic: license-file
